aiclient/__init__.py
aiclient/agent.py
aiclient/batch.py
aiclient/client.py
aiclient/data_types.py
aiclient/exceptions.py
aiclient/middleware.py
aiclient/observability.py
aiclient/testing.py
aiclient/utils.py
aiclient/agents/__init__.py
aiclient/agents/simple.py
aiclient/cache/__init__.py
aiclient/cache/semantic.py
aiclient/mcp/__init__.py
aiclient/mcp/client.py
aiclient/mcp/manager.py
aiclient/memory/__init__.py
aiclient/memory/base.py
aiclient/memory/simple.py
aiclient/models/__init__.py
aiclient/models/chat.py
aiclient/providers/anthropic.py
aiclient/providers/base.py
aiclient/providers/google.py
aiclient/providers/ollama.py
aiclient/providers/openai.py
aiclient/resilience/__init__.py
aiclient/resilience/retries.py
aiclient/tools/__init__.py
aiclient/tools/base.py
aiclient/tools/policy.py
aiclient/transport/__init__.py
aiclient/transport/base.py
aiclient/transport/http.py
aiclient_llm-0.2.2.dist-info/METADATA
aiclient_llm-0.2.2.dist-info/WHEEL
aiclient_llm-0.2.2.dist-info/licenses/LICENSE
aiclient_llm-0.2.2.dist-info/RECORD
