Metadata-Version: 2.4
Name: aiclient-llm
Version: 0.2.2
Summary: A minimal, generic client for AI models (OpenAI, Anthropic, Google, xAI) with middleware support.
Project-URL: Homepage, https://github.com/rarenicks/aiclient
Project-URL: Documentation, https://github.com/rarenicks/aiclient/tree/main/docs
Project-URL: Repository, https://github.com/rarenicks/aiclient
Project-URL: Issues, https://github.com/rarenicks/aiclient/issues
Project-URL: Changelog, https://github.com/rarenicks/aiclient/blob/main/CHANGELOG.md
Author-email: Avdhesh Singh Chouhan <ai.avdhesh@gmail.com>
License-Expression: Apache-2.0
License-File: LICENSE
Keywords: ai,anthropic,client,gemini,llm,openai
Classifier: Development Status :: 3 - Alpha
Classifier: Programming Language :: Python
Classifier: Programming Language :: Python :: 3.10
Classifier: Programming Language :: Python :: 3.11
Classifier: Programming Language :: Python :: Implementation :: CPython
Classifier: Programming Language :: Python :: Implementation :: PyPy
Requires-Python: >=3.10
Requires-Dist: httpx>=0.25.0
Requires-Dist: mcp>=1.0.0
Requires-Dist: numpy>=1.20.0
Requires-Dist: pydantic>=2.0
Requires-Dist: python-dotenv
Provides-Extra: dev
Requires-Dist: mypy; extra == 'dev'
Requires-Dist: pytest; extra == 'dev'
Requires-Dist: ruff; extra == 'dev'
